dserver_minimal/__init__.py
dserver_minimal/version.py
dserver_minimal-0.2.0.dist-info/LICENSE
dserver_minimal-0.2.0.dist-info/METADATA
dserver_minimal-0.2.0.dist-info/WHEEL
dserver_minimal-0.2.0.dist-info/top_level.txt
dserver_minimal-0.2.0.dist-info/RECORD
