Metadata-Version: 2.1
Name: dserver-minimal
Version: 0.2.0
Summary: Meta-package for installing a minimal working dserver consisting of dservercore, dserver-search-plugin-mongo, and dserver-retrieve-plugin-mongo
Author-email: Tjelvar Olsson <tjelvar.olsson@gmail.com>, "Johannes L. Hörmann" <johannes.laurin@gmail.com>
License: MIT License
Project-URL: Documentation, https://dserver.readthedocs.io
Project-URL: Repository, https://github.com/livMatS/dserver-minimal
Project-URL: Changelog, https://github.com/livMatS/dserver-minimal/blob/main/CHANGELOG.rst
License-File: LICENSE
Requires-Dist: dservercore >=0.2.0
Requires-Dist: dserver-search-plugin-mongo >=0.4.0
Requires-Dist: dserver-retrieve-plugin-mongo >=0.4.0
Provides-Extra: docs
Requires-Dist: sphinx ; extra == 'docs'
Requires-Dist: sphinx-rtd-theme ; extra == 'docs'
Requires-Dist: sphinxcontrib-spelling ; extra == 'docs'
Requires-Dist: sphinxcontrib-bibtex ; extra == 'docs'
Requires-Dist: myst-parser ==2.0.0 ; extra == 'docs'
